{"examples_dependent-schedules_index.md":"150d073c","about_approach.md":"40736853","guide_component.md":"3a63595a","guide_element.md":"b35f8b9f","examples_index.md":"6a333571","guide_installation.md":"59aa7ee4","reference_index.md":"a073225b","guide_interface.md":"5c24027f","guide_introduction.md":"baf96e4d","index.md":"ec5fddb7","examples_aimstack-storage_index.md":"f9cfa005","examples_globus-storage_index.md":"f366404a","examples_require-execution_index.md":"e31ee6e4","examples_mpi-execution_index.md":"afc18990","examples_slurm-execution_index.md":"2dac90d8"}
