{"about_approach.md":"40736853","examples_checkpointing_index.md":"8cb49f04","examples_dependent-schedules_index.md":"150d073c","examples_aim-ui-storage_index.md":"5466fe15","guide_introduction.md":"f7a4c62b","examples_globus-storage_index.md":"48693383","guide_interface.md":"92d40bc2","examples_index.md":"6a333571","guide_installation.md":"59aa7ee4","reference_index.md":"a073225b","index.md":"ec5fddb7","guide_component.md":"1f1b9596","guide_element.md":"b35f8b9f","examples_slurm-and-mpi-execution_index.md":"b530f9ff"}
