{"about_approach.md":"40736853","index.md":"ec5fddb7","examples_globus-storage_index.md":"5f50a34a","examples_mpi-execution_index.md":"644cb8f9","guide_installation.md":"59aa7ee4","guide_introduction.md":"8f71174b","guide_component.md":"dea33283","examples_dependent-schedules_index.md":"150d073c","reference_index.md":"a073225b","examples_index.md":"6a333571","examples_slurm-execution_index.md":"741b2324","guide_element.md":"b35f8b9f","guide_interface.md":"593f9aeb","examples_aimstack-storage_index.md":"cda261fe","examples_require-execution_index.md":"74ddac1a"}
